ddcUtils/__init__.py
ddcUtils/conf_file_utils.py
ddcUtils/constants.py
ddcUtils/file_utils.py
ddcUtils/misc_utils.py
ddcUtils/os_utils.py
ddcutils-2.0.0.dist-info/LICENSE
ddcutils-2.0.0.dist-info/METADATA
ddcutils-2.0.0.dist-info/WHEEL
ddcutils-2.0.0.dist-info/RECORD
