Metadata-Version: 2.3
Name: ddcUtils
Version: 2.0.0
Summary: Few File Utilities and some OS Functions
License: MIT
Keywords: python3,python-3,python,tools,utility,utilities,utils,utility-library,utils-library,utilities-library
Author: Daniel Costa
Author-email: danieldcsta@gmail.com
Maintainer: Daniel Costa
Requires-Python: >=3.12,<4.0
Classifier: Development Status :: 5 - Production/Stable
Classifier: Environment :: Other Environment
Classifier: Intended Audience :: Developers
Classifier: License :: OSI Approved :: MIT License
Classifier: Natural Language :: English
Classifier: Operating System :: OS Independent
Classifier: Programming Language :: Python :: 3
Classifier: Programming Language :: Python :: 3.12
Classifier: Programming Language :: Python :: 3.13
Classifier: Programming Language :: Python :: 3 :: Only
Classifier: Topic :: Software Development :: Libraries :: Python Modules
Requires-Dist: requests (>=2.32.4,<3.0.0)
Project-URL: Homepage, https://pypi.org/project/ddcUtils
Project-URL: Repository, https://github.com/ddc/ddcUtils
